jupyterlab_log_renderer/__init__.py
jupyterlab_log_renderer/_version.py
jupyterlab_log_renderer/handler.py
jupyterlab_log_renderer/labextension/package.json
jupyterlab_log_renderer/labextension/static/549.e431ac5f6ce49c18d49b.js
jupyterlab_log_renderer/labextension/static/930.174cfea28ce3c313c346.js
jupyterlab_log_renderer/labextension/static/remoteEntry.1a2d6c75681907b77196.js
jupyterlab_log_renderer/labextension/static/style.js
jupyterlab_log_renderer-2.0.0.data/data/share/jupyter/labextensions/@agoose77/jupyterlab_log_renderer/install.json
jupyterlab_log_renderer-2.0.0.data/data/share/jupyter/labextensions/@agoose77/jupyterlab_log_renderer/package.json
jupyterlab_log_renderer-2.0.0.data/data/share/jupyter/labextensions/@agoose77/jupyterlab_log_renderer/static/549.e431ac5f6ce49c18d49b.js
jupyterlab_log_renderer-2.0.0.data/data/share/jupyter/labextensions/@agoose77/jupyterlab_log_renderer/static/930.174cfea28ce3c313c346.js
jupyterlab_log_renderer-2.0.0.data/data/share/jupyter/labextensions/@agoose77/jupyterlab_log_renderer/static/remoteEntry.1a2d6c75681907b77196.js
jupyterlab_log_renderer-2.0.0.data/data/share/jupyter/labextensions/@agoose77/jupyterlab_log_renderer/static/style.js
jupyterlab_log_renderer-2.0.0.dist-info/LICENSE
jupyterlab_log_renderer-2.0.0.dist-info/METADATA
jupyterlab_log_renderer-2.0.0.dist-info/WHEEL
jupyterlab_log_renderer-2.0.0.dist-info/top_level.txt
jupyterlab_log_renderer-2.0.0.dist-info/RECORD
