Metadata-Version: 2.1
Name: jupyterlab-log-renderer
Version: 2.0.0
Summary: A JupyterLab extension to render rich-display objects to the JupyterLab log window.
Home-page: https://github.com/agoose77/jupyterlab-log-renderer.git
Author: Angus Hollands
License: BSD-3-Clause
Keywords: Jupyter,JupyterLab,JupyterLab3
Platform: Linux
Platform: Mac OS X
Platform: Windows
Classifier: License :: OSI Approved :: BSD License
Classifier: Programming Language :: Python
Classifier: Programming Language :: Python :: 3
Classifier: Programming Language :: Python :: 3.6
Classifier: Programming Language :: Python :: 3.7
Classifier: Programming Language :: Python :: 3.8
Classifier: Framework :: Jupyter
Requires-Python: >=3.6
Requires-Dist: jupyterlab (==3.*,>=3.0.0rc13)
